{"name":"capybara","typeLevel":1,"totalToWin":71,"buttonConfigs":[{"buttonHex":"#4C3618","fontHex":"#FFFFFF"},{"buttonHex":"#9C6838","fontHex":"#000000"}],"boxConfigs":[[{"mainHex":"#FFFFFF","extraHex":"#FFFFFF"},{"mainHex":"#FFFFFF","extraHex":"#FFFFFF"},{"mainHex":"#FFFFFF","extraHex":"#FFFFFF"},{"mainHex":"#4C3618","extraHex":"#4D3618"},{"mainHex":"#4C3618","extraHex":"#4E3417"},{"mainHex":"#4C3618","extraHex":"#4E3417"},{"mainHex":"#FFFFFF","extraHex":"#FFFFFF"},{"mainHex":"#FFFFFF","extraHex":"#FFFFFF"},{"mainHex":"#FFFFFF","extraHex":"#FFFFFF"},{"mainHex":"#FFFFFF","extraHex":"#FFFFFF"}],[{"mainHex":"#FFFFFF","extraHex":"#FFFFFF"},{"mainHex":"#FFFFFF","extraHex":"#FFFFFF"},{"mainHex":"#FFFFFF","extraHex":"#FFFFFF"},{"mainHex":"#4C3618","extraHex":"#4D3618"},{"mainHex":"#9C6838","extraHex":"#96652C"},{"mainHex":"#9C6838","extraHex":"#96652C"},{"mainHex":"#4C3618","extraHex":"#4B3118"},{"mainHex":"#4C3618","extraHex":"#4B3118"},{"mainHex":"#4C3618","extraHex":"#4B3118"},{"mainHex":"#FFFFFF","extraHex":"#FFFFFF"}],[{"mainHex":"#FFFFFF","extraHex":"#FFFFFF"},{"mainHex":"#FFFFFF","extraHex":"#FFFFFF"},{"mainHex":"#FFFFFF","extraHex":"#FFFFFF"},{"mainHex":"#FFFFFF","extraHex":"#FFFFFF"},{"mainHex":"#4C3618","extraHex":"#4E3417"},{"mainHex":"#9C6838","extraHex":"#96652C"},{"mainHex":"#9C6838","extraHex":"#8B5C2E"},{"mainHex":"#9C6838","extraHex":"#8B5C2E"},{"mainHex":"#9C6838","extraHex":"#8B5C2E"},{"mainHex":"#4C3618","extraHex":"#4B3118"}],[{"mainHex":"#FFFFFF","extraHex":"#FFFFFF"},{"mainHex":"#FFFFFF","extraHex":"#FFFFFF"},{"mainHex":"#4C3618","extraHex":"#4D3618"},{"mainHex":"#4C3618","extraHex":"#4D3618"},{"mainHex":"#4C3618","extraHex":"#4D3618"},{"mainHex":"#9C6838","extraHex":"#96652C"},{"mainHex":"#FFFFFF","extraHex":"#25180C"},{"mainHex":"#FFFFFF","extraHex":"#25180C"},{"mainHex":"#9C6838","extraHex":"#8B5C2E"},{"mainHex":"#FFFFFF","extraHex":"#583A1D"}],[{"mainHex":"#FFFFFF","extraHex":"#FFFFFF"},{"mainHex":"#4C3618","extraHex":"#4D331B"},{"mainHex":"#9C6838","extraHex":"#9E6938"},{"mainHex":"#9C6838","extraHex":"#9E6938"},{"mainHex":"#9C6838","extraHex":"#9E6938"},{"mainHex":"#9C6838","extraHex":"#9E6938"},{"mainHex":"#9C6838","extraHex":"#9E6934"},{"mainHex":"#9C6838","extraHex":"#9E6934"},{"mainHex":"#9C6838","extraHex":"#9E6934"},{"mainHex":"#4C3618","extraHex":"#4D3319"}],[{"mainHex":"#4C3618","extraHex":"#4D3618"},{"mainHex":"#9C6838","extraHex":"#9E6938"},{"mainHex":"#9C6838","extraHex":"#9E6938"},{"mainHex":"#9C6838","extraHex":"#9E6938"},{"mainHex":"#9C6838","extraHex":"#9E6938"},{"mainHex":"#9C6838","extraHex":"#9E6938"},{"mainHex":"#9C6838","extraHex":"#9E6934"},{"mainHex":"#9C6838","extraHex":"#9E6934"},{"mainHex":"#9C6838","extraHex":"#9E6934"},{"mainHex":"#4C3618","extraHex":"#4D3319"}],[{"mainHex":"#4C3618","extraHex":"#4D3618"},{"mainHex":"#9C6838","extraHex":"#9E6938"},{"mainHex":"#9C6838","extraHex":"#9E6938"},{"mainHex":"#4C3618","extraHex":"#4D331B"},{"mainHex":"#9C6838","extraHex":"#9E6938"},{"mainHex":"#9C6838","extraHex":"#9E6938"},{"mainHex":"#9C6838","extraHex":"#9E6934"},{"mainHex":"#4C3618","extraHex":"#4D3319"},{"mainHex":"#4C3618","extraHex":"#4D3319"},{"mainHex":"#FFFFFF","extraHex":"#FFFFFF"}],[{"mainHex":"#4C3618","extraHex":"#4D3618"},{"mainHex":"#9C6838","extraHex":"#9E6938"},{"mainHex":"#9C6838","extraHex":"#9E6938"},{"mainHex":"#9C6838","extraHex":"#9E6938"},{"mainHex":"#4C3618","extraHex":"#4D331B"},{"mainHex":"#9C6838","extraHex":"#9E6938"},{"mainHex":"#9C6838","extraHex":"#9E6934"},{"mainHex":"#4C3618","extraHex":"#4D3319"},{"mainHex":"#FFFFFF","extraHex":"#FFFFFF"},{"mainHex":"#FFFFFF","extraHex":"#FFFFFF"}],[{"mainHex":"#4C3618","extraHex":"#4D3618"},{"mainHex":"#9C6838","extraHex":"#9E6938"},{"mainHex":"#9C6838","extraHex":"#9E6938"},{"mainHex":"#4C3618","extraHex":"#4D331B"},{"mainHex":"#4C3618","extraHex":"#4D331B"},{"mainHex":"#9C6838","extraHex":"#9E6938"},{"mainHex":"#9C6838","extraHex":"#9E6934"},{"mainHex":"#4C3618","extraHex":"#4D3319"},{"mainHex":"#FFFFFF","extraHex":"#FFFFFF"},{"mainHex":"#FFFFFF","extraHex":"#FFFFFF"}],[{"mainHex":"#FFFFFF","extraHex":"#FFFFFF"},{"mainHex":"#4C3618","extraHex":"#4D331B"},{"mainHex":"#9C6838","extraHex":"#9E6938"},{"mainHex":"#9C6838","extraHex":"#9E6938"},{"mainHex":"#4C3618","extraHex":"#4D331B"},{"mainHex":"#4C3618","extraHex":"#4D331B"},{"mainHex":"#9C6838","extraHex":"#9E6934"},{"mainHex":"#4C3618","extraHex":"#4D3618"},{"mainHex":"#FFFFFF","extraHex":"#FFFFFF"},{"mainHex":"#FFFFFF","extraHex":"#FFFFFF"}]]}