{"name":"rooster","typeLevel":1,"totalToWin":40,"buttonConfigs":[{"buttonHex":"#B22422","fontHex":"#FFFFFF"},{"buttonHex":"#FEAD00","fontHex":"#000000"},{"buttonHex":"#5C565A","fontHex":"#FFFFFF"},{"buttonHex":"#2E2F29","fontHex":"#FFFFFF"}],"boxConfigs":[[{"mainHex":"#FFFFFF","extraHex":"#FFFFFF"},{"mainHex":"#FFFFFF","extraHex":"#FFFFFF"},{"mainHex":"#FFFFFF","extraHex":"#FFFFFF"},{"mainHex":"#FFFFFF","extraHex":"#BA2E17"},{"mainHex":"#FFFFFF","extraHex":"#FFFFFF"},{"mainHex":"#FFFFFF","extraHex":"#FFFFFF"},{"mainHex":"#FFFFFF","extraHex":"#FFFFFF"},{"mainHex":"#FFFFFF","extraHex":"#FFFFFF"},{"mainHex":"#FFFFFF","extraHex":"#FFFFFF"},{"mainHex":"#FFFFFF","extraHex":"#FFFFFF"}],[{"mainHex":"#FFFFFF","extraHex":"#FFFFFF"},{"mainHex":"#FFFFFF","extraHex":"#FFFFFF"},{"mainHex":"#FFFFFF","extraHex":"#BA2E17"},{"mainHex":"#FFFFFF","extraHex":"#BA2E17"},{"mainHex":"#FFFFFF","extraHex":"#BA2E17"},{"mainHex":"#FFFFFF","extraHex":"#FFFFFF"},{"mainHex":"#FFFFFF","extraHex":"#FFFFFF"},{"mainHex":"#FFFFFF","extraHex":"#FFFFFF"},{"mainHex":"#FFFFFF","extraHex":"#FFFFFF"},{"mainHex":"#FFFFFF","extraHex":"#FFFFFF"}],[{"mainHex":"#FFFFFF","extraHex":"#FFFFFF"},{"mainHex":"#FFFFFF","extraHex":"#FFFFFF"},{"mainHex":"#5C565A","extraHex":"#5B5B5B"},{"mainHex":"#5C565A","extraHex":"#5B5B5B"},{"mainHex":"#5C565A","extraHex":"#5B5B5B"},{"mainHex":"#FFFFFF","extraHex":"#FFFFFF"},{"mainHex":"#FFFFFF","extraHex":"#FFFFFF"},{"mainHex":"#FFFFFF","extraHex":"#FFFFFF"},{"mainHex":"#FFFFFF","extraHex":"#FFFFFF"},{"mainHex":"#5C565A","extraHex":"#5C565A"}],[{"mainHex":"#FFFFFF","extraHex":"#FFFFFF"},{"mainHex":"#FEAD00","extraHex":"#FFA300"},{"mainHex":"#5C565A","extraHex":"#5B5B5B"},{"mainHex":"#5C565A","extraHex":"#5B5B5B"},{"mainHex":"#5C565A","extraHex":"#5B5B5B"},{"mainHex":"#FFFFFF","extraHex":"#FFFFFF"},{"mainHex":"#FFFFFF","extraHex":"#FFFFFF"},{"mainHex":"#FFFFFF","extraHex":"#FFFFFF"},{"mainHex":"#5C565A","extraHex":"#5C565A"},{"mainHex":"#5C565A","extraHex":"#5C565A"}],[{"mainHex":"#FEAD00","extraHex":"#FFA300"},{"mainHex":"#FEAD00","extraHex":"#FFA300"},{"mainHex":"#5C565A","extraHex":"#5C5C5C"},{"mainHex":"#5C565A","extraHex":"#5C5C5C"},{"mainHex":"#5C565A","extraHex":"#5C5C5C"},{"mainHex":"#5C565A","extraHex":"#5C5C5C"},{"mainHex":"#FFFFFF","extraHex":"#554455"},{"mainHex":"#5C565A","extraHex":"#555555"},{"mainHex":"#5C565A","extraHex":"#555555"},{"mainHex":"#5C565A","extraHex":"#555555"}],[{"mainHex":"#FFFFFF","extraHex":"#FFFFFF"},{"mainHex":"#FFFFFF","extraHex":"#FFFFFF"},{"mainHex":"#5C565A","extraHex":"#5B5B5B"},{"mainHex":"#5C565A","extraHex":"#5B5B5B"},{"mainHex":"#5C565A","extraHex":"#5B5B5B"},{"mainHex":"#5C565A","extraHex":"#5B5B5B"},{"mainHex":"#FFFFFF","extraHex":"#554455"},{"mainHex":"#2E2F29","extraHex":"#2D2D2D"},{"mainHex":"#5C565A","extraHex":"#555555"},{"mainHex":"#5C565A","extraHex":"#555555"}],[{"mainHex":"#FFFFFF","extraHex":"#FFFFFF"},{"mainHex":"#FFFFFF","extraHex":"#FFFFFF"},{"mainHex":"#5C565A","extraHex":"#5B5B5B"},{"mainHex":"#5C565A","extraHex":"#5B5B5B"},{"mainHex":"#5C565A","extraHex":"#5B5B5B"},{"mainHex":"#5C565A","extraHex":"#5B5B5B"},{"mainHex":"#FFFFFF","extraHex":"#554455"},{"mainHex":"#5C565A","extraHex":"#545454"},{"mainHex":"#5C565A","extraHex":"#545454"},{"mainHex":"#FFFFFF","extraHex":"#FFFFFF"}],[{"mainHex":"#FFFFFF","extraHex":"#FFFFFF"},{"mainHex":"#FFFFFF","extraHex":"#FFFFFF"},{"mainHex":"#FFFFFF","extraHex":"#FFFFFF"},{"mainHex":"#5C565A","extraHex":"#5B5B5B"},{"mainHex":"#5C565A","extraHex":"#5B5B5B"},{"mainHex":"#5C565A","extraHex":"#5B5B5B"},{"mainHex":"#FFFFFF","extraHex":"#554455"},{"mainHex":"#5C565A","extraHex":"#545454"},{"mainHex":"#FFFFFF","extraHex":"#FFFFFF"},{"mainHex":"#FFFFFF","extraHex":"#FFFFFF"}],[{"mainHex":"#FFFFFF","extraHex":"#FFFFFF"},{"mainHex":"#FFFFFF","extraHex":"#FFFFFF"},{"mainHex":"#FFFFFF","extraHex":"#FFFFFF"},{"mainHex":"#FFFFFF","extraHex":"#FFFFFF"},{"mainHex":"#FEAD00","extraHex":"#FFA300"},{"mainHex":"#FFFFFF","extraHex":"#FFFFFF"},{"mainHex":"#FEAD00","extraHex":"#FFAA00"},{"mainHex":"#FFFFFF","extraHex":"#FFFFFF"},{"mainHex":"#FFFFFF","extraHex":"#FFFFFF"},{"mainHex":"#FFFFFF","extraHex":"#FFFFFF"}],[{"mainHex":"#FFFFFF","extraHex":"#FFFFFF"},{"mainHex":"#FFFFFF","extraHex":"#FFFFFF"},{"mainHex":"#FFFFFF","extraHex":"#FFFFFF"},{"mainHex":"#FFFFFF","extraHex":"#FFFFFF"},{"mainHex":"#FEAD00","extraHex":"#FFA300"},{"mainHex":"#FFFFFF","extraHex":"#FFFFFF"},{"mainHex":"#FEAD00","extraHex":"#FFAA00"},{"mainHex":"#FFFFFF","extraHex":"#FFFFFF"},{"mainHex":"#FFFFFF","extraHex":"#FFFFFF"},{"mainHex":"#FFFFFF","extraHex":"#FFFFFF"}]]}