{"name":"koala","typeLevel":1,"totalToWin":44,"buttonConfigs":[{"buttonHex":"#BDC9BD","fontHex":"#000000"},{"buttonHex":"#010002","fontHex":"#FFFFFF"},{"buttonHex":"#88C53A","fontHex":"#000000"},{"buttonHex":"#C25540","fontHex":"#000000"}],"boxConfigs":[[{"mainHex":"#FFFFFF","extraHex":"#BEBFBE"},{"mainHex":"#FFFFFF","extraHex":"#BEBFBE"},{"mainHex":"#FFFFFF","extraHex":"#BEBFBE"},{"mainHex":"#FFFFFF","extraHex":"#FDFFFD"},{"mainHex":"#FFFFFF","extraHex":"#FDFFFD"},{"mainHex":"#FFFFFF","extraHex":"#BEBFBE"},{"mainHex":"#BDC9BD","extraHex":"#BFC0BF"},{"mainHex":"#FFFFFF","extraHex":"#FDFFFD"},{"mainHex":"#FFFFFF","extraHex":"#FDFFFD"},{"mainHex":"#BDC9BD","extraHex":"#BFC0BF"}],[{"mainHex":"#FFFFFF","extraHex":"#BEBFBE"},{"mainHex":"#FFFFFF","extraHex":"#FDFFFD"},{"mainHex":"#FFFFFF","extraHex":"#BEBFBE"},{"mainHex":"#FFFFFF","extraHex":"#BEBFBE"},{"mainHex":"#FFFFFF","extraHex":"#BEBFBE"},{"mainHex":"#FFFFFF","extraHex":"#BEBFBE"},{"mainHex":"#BDC9BD","extraHex":"#BFC0BF"},{"mainHex":"#BDC9BD","extraHex":"#BFC0BF"},{"mainHex":"#BDC9BD","extraHex":"#BFC0BF"},{"mainHex":"#BDC9BD","extraHex":"#BFC0BF"}],[{"mainHex":"#FFFFFF","extraHex":"#BEBFBE"},{"mainHex":"#FFFFFF","extraHex":"#BEBFBE"},{"mainHex":"#FFFFFF","extraHex":"#BEBFBE"},{"mainHex":"#FFFFFF","extraHex":"#BEBFBE"},{"mainHex":"#FFFFFF","extraHex":"#FDFFFD"},{"mainHex":"#FFFFFF","extraHex":"#BEBFBE"},{"mainHex":"#BDC9BD","extraHex":"#BFC0BF"},{"mainHex":"#FFFFFF","extraHex":"#FDFFFD"},{"mainHex":"#BDC9BD","extraHex":"#BFC0BF"},{"mainHex":"#BDC9BD","extraHex":"#BFC0BF"}],[{"mainHex":"#FFFFFF","extraHex":"#FDFFFD"},{"mainHex":"#FFFFFF","extraHex":"#FDFFFD"},{"mainHex":"#FFFFFF","extraHex":"#BEBFBE"},{"mainHex":"#FFFFFF","extraHex":"#BEBFBE"},{"mainHex":"#010002","extraHex":"#010101"},{"mainHex":"#FFFFFF","extraHex":"#BEBFBE"},{"mainHex":"#BDC9BD","extraHex":"#BFC0BF"},{"mainHex":"#010002","extraHex":"#040404"},{"mainHex":"#BDC9BD","extraHex":"#BFC0BF"},{"mainHex":"#BDC9BD","extraHex":"#BFC0BF"}],[{"mainHex":"#FFFFFF","extraHex":"#FFFFFF"},{"mainHex":"#FFFFFF","extraHex":"#FFFFFF"},{"mainHex":"#FFFFFF","extraHex":"#BBBBBB"},{"mainHex":"#BDC9BD","extraHex":"#BBCCBB"},{"mainHex":"#BDC9BD","extraHex":"#BBCCBB"},{"mainHex":"#010002","extraHex":"#000000"},{"mainHex":"#010002","extraHex":"#000000"},{"mainHex":"#FFFFFF","extraHex":"#B6DBB6"},{"mainHex":"#FFFFFF","extraHex":"#B6DBB6"},{"mainHex":"#FFFFFF","extraHex":"#B64949"}],[{"mainHex":"#FFFFFF","extraHex":"#FFFFFF"},{"mainHex":"#FFFFFF","extraHex":"#BBBBBB"},{"mainHex":"#BDC9BD","extraHex":"#BBCCBB"},{"mainHex":"#BDC9BD","extraHex":"#BBCCBB"},{"mainHex":"#BDC9BD","extraHex":"#BBCCBB"},{"mainHex":"#010002","extraHex":"#000000"},{"mainHex":"#010002","extraHex":"#000000"},{"mainHex":"#FFFFFF","extraHex":"#B6DBB6"},{"mainHex":"#FFFFFF","extraHex":"#B64949"},{"mainHex":"#FFFFFF","extraHex":"#B64949"}],[{"mainHex":"#FFFFFF","extraHex":"#BBBBBB"},{"mainHex":"#BDC9BD","extraHex":"#BBCCBB"},{"mainHex":"#BDC9BD","extraHex":"#BBCCBB"},{"mainHex":"#BDC9BD","extraHex":"#BBCCBB"},{"mainHex":"#BDC9BD","extraHex":"#BBCCBB"},{"mainHex":"#BDC9BD","extraHex":"#BBCCBB"},{"mainHex":"#FFFFFF","extraHex":"#FFFFFF"},{"mainHex":"#FFFFFF","extraHex":"#B64949"},{"mainHex":"#FFFFFF","extraHex":"#B64949"},{"mainHex":"#FFFFFF","extraHex":"#B64949"}],[{"mainHex":"#BDC9BD","extraHex":"#BBCCBB"},{"mainHex":"#BDC9BD","extraHex":"#BBCCBB"},{"mainHex":"#BDC9BD","extraHex":"#BBCCBB"},{"mainHex":"#BDC9BD","extraHex":"#BBCCBB"},{"mainHex":"#FFFFFF","extraHex":"#7E897E"},{"mainHex":"#FFFFFF","extraHex":"#7E897E"},{"mainHex":"#FFFFFF","extraHex":"#B64949"},{"mainHex":"#FFFFFF","extraHex":"#B64949"},{"mainHex":"#FFFFFF","extraHex":"#B64949"},{"mainHex":"#FFFFFF","extraHex":"#FFFFFF"}],[{"mainHex":"#BDC9BD","extraHex":"#BBCCBB"},{"mainHex":"#FFFFFF","extraHex":"#7E897E"},{"mainHex":"#BDC9BD","extraHex":"#BBCCBB"},{"mainHex":"#BDC9BD","extraHex":"#BBCCBB"},{"mainHex":"#BDC9BD","extraHex":"#BBCCBB"},{"mainHex":"#BDC9BD","extraHex":"#BBCCBB"},{"mainHex":"#FFFFFF","extraHex":"#FFFFFF"},{"mainHex":"#010002","extraHex":"#000000"},{"mainHex":"#FFFFFF","extraHex":"#FFFFFF"},{"mainHex":"#FFFFFF","extraHex":"#FFFFFF"}],[{"mainHex":"#BDC9BD","extraHex":"#BBCCBB"},{"mainHex":"#BDC9BD","extraHex":"#BBCCBB"},{"mainHex":"#FFFFFF","extraHex":"#7E897E"},{"mainHex":"#BDC9BD","extraHex":"#BBCCBB"},{"mainHex":"#BDC9BD","extraHex":"#BBCCBB"},{"mainHex":"#BDC9BD","extraHex":"#BBCCBB"},{"mainHex":"#010002","extraHex":"#000000"},{"mainHex":"#FFFFFF","extraHex":"#92B649"},{"mainHex":"#FFFFFF","extraHex":"#92B649"},{"mainHex":"#FFFFFF","extraHex":"#92B649"}]]}